{
  "word": "alaska",
  "pronunciation": "uh·lask·uh",
  "concise_definition": "n. 阿拉斯加（美国州名）",
  "forms": {
    "proper_noun": "Alaska"
  },
  "definitions": [
    {
      "pos": "noun",
      "explanation_en": "The largest state in the United States by area, located in the northwest extremity of North America, known for its vast wilderness, glaciers, wildlife, and rich Indigenous cultures.",
      "explanation_cn": "美国面积最大的州，位于北美洲西北端，以其广袤的荒野、冰川、野生动物和丰富的原住民文化而闻名。",
      "example_en": "Many tourists visit Alaska to see bears in the wild and witness the northern lights.",
      "example_cn": "许多游客前往阿拉斯加，以在野外观赏熊群并目睹极光。"
    },
    {
      "pos": "noun",
      "explanation_en": "A region or place metaphorically used to describe something remote, cold, or sparsely populated.",
      "explanation_cn": "比喻性地用于形容某个偏远、寒冷或人烟稀少的地方。",
      "example_en": "After the company moved its headquarters, the old office felt like Alaska—abandoned and forgotten.",
      "example_cn": "公司搬迁总部后，旧办公室就像阿拉斯加一样——被遗弃且无人问津。"
    }
  ],
  "comparison": [
    {
      "word_to_compare": "hawaii",
      "analysis": "“Hawaii”（夏威夷）是美国另一个州，位于太平洋中部，以热带气候、海滩和火山地貌著称，与阿拉斯加的寒冷荒野形成鲜明对比。两者虽同为美国州份，但地理、气候和文化特征截然不同。"
    },
    {
      "word_to_compare": "canada",
      "analysis": "“Canada”（加拿大）是美国北部的邻国，与阿拉斯加接壤，但加拿大是一个主权国家，拥有多个省份和更复杂的政治结构。阿拉斯加是美国的一个州，虽地理上靠近加拿大，但行政归属不同。"
    },
    {
      "word_to_compare": "antarctica",
      "analysis": "“Antarctica”（南极洲）是地球上最寒冷、最偏远的大陆，常被类比为“地球的阿拉斯加”。但南极洲无常住人口，不属于任何国家，而阿拉斯加是有人居住、经济活跃的美国州份。两者虽都寒冷，但社会与法律地位完全不同。"
    }
  ]
}