{
  "word": "arizona",
  "pronunciation": "ar·uh·zoh·nuh",
  "concise_definition": "n. 亚利桑那州（美国西南部的一个州）",
  "forms": {
    "proper_noun": true
  },
  "definitions": [
    {
      "pos": "noun",
      "explanation_en": "A state in the southwestern region of the United States, known for its desert landscapes, the Grand Canyon, and a hot, dry climate.",
      "explanation_cn": "美国西南部的一个州，以沙漠地貌、大峡谷以及炎热干燥的气候而闻名。",
      "example_en": "We spent our vacation hiking through the Grand Canyon in Arizona.",
      "example_cn": "我们假期在亚利桑那州的大峡谷徒步旅行。"
    },
    {
      "pos": "noun",
      "explanation_en": "A cultural and geographic region associated with the American Southwest, often symbolizing rugged natural beauty, Native American heritage, and cowboy traditions.",
      "explanation_cn": "与美国西南部相关的一种文化和地理区域，常象征着粗犷的自然美景、美洲原住民遗产和牛仔传统。",
      "example_en": "The architecture of the resort reflects classic Arizona style with adobe walls and red-tiled roofs.",
      "example_cn": "度假村的建筑采用了典型的亚利桑那风格，配有泥砖墙和红色陶瓦屋顶。"
    }
  ],
  "comparison": [
    {
      "word_to_compare": "nevada",
      "analysis": "“Nevada”（内华达州）与亚利桑那州相邻，同属美国西南部，但内华达以拉斯维加斯的娱乐业和更干旱的盆地地貌著称，而亚利桑那则以大峡谷和更丰富的原住民文化闻名。两者气候相似，但亚利桑那的自然景观更具标志性。"
    },
    {
      "word_to_compare": "california",
      "analysis": "“California”（加利福尼亚州）位于亚利桑那州西部，经济和人口规模远超亚利桑那，以科技、娱乐和多元文化著称。亚利桑那则更偏向自然与休闲旅游，城市化程度较低，保留了更多沙漠与原住民传统。"
    },
    {
      "word_to_compare": "new mexico",
      "analysis": "“New Mexico”（新墨西哥州）与亚利桑那共享部分文化特征，如普韦布洛原住民艺术和西班牙殖民遗产，但新墨西哥的海拔更高、气候更凉爽，且西班牙语影响更深。亚利桑那则更强调沙漠生态和大峡谷的自然奇观。"
    }
  ]
}