{
  "word": "connie",
  "pronunciation": "kɒˈni",
  "concise_definition": "n. (人名) 康妮",
  "forms": {
    "plural": "connies"
  },
  "definitions": [
    {
      "pos": "noun",
      "explanation_en": "A proper noun used as a given name, typically feminine, often a diminutive form of names like Constance or Connie as a standalone name.",
      "explanation_cn": "用作女性人名的专有名词，通常是 Constance 的昵称或独立使用的名字，常见于英语国家。",
      "example_en": "Connie is the lead singer in the band and has a powerful voice.",
      "example_cn": "康妮是这支乐队的主唱，拥有极具穿透力的嗓音。"
    },
    {
      "pos": "noun",
      "explanation_en": "In some contexts, 'Connie' may refer to a specific character in literature, film, or popular culture, often portrayed as warm, spirited, or resilient.",
      "explanation_cn": "在某些语境中，'Connie' 可指文学、电影或流行文化中的特定角色，常被描绘为热情、有活力或坚韧的人物。",
      "example_en": "In The Godfather, Connie Corleone is a complex character whose journey reflects the cost of family loyalty.",
      "example_cn": "在《教父》中，康妮·柯里昂是一个复杂的角色，她的经历反映了家族忠诚所付出的代价。"
    }
  ],
  "comparison": [
    {
      "word_to_compare": "Constance",
      "analysis": "“Constance” 是 “Connie” 的完整形式，源自拉丁语，意为“坚定、恒常”，更具正式和古典色彩。而 “Connie” 是其口语化、亲昵的缩略形式，常用于日常交流，语气更轻松、亲切。"
    },
    {
      "word_to_compare": "Bonnie",
      "analysis": "“Bonnie” 与 “Connie” 同为女性昵称，但 “Bonnie” 源自苏格兰语，意为“美丽、愉快”，常带有活泼、可爱的联想；而 “Connie” 更偏向稳重、内敛的气质，尤其在文化作品中常呈现复杂性格。"
    },
    {
      "word_to_compare": "Dottie",
      "analysis": "“Dottie” 是 Dorothy 的昵称，常用于老一辈女性，带有怀旧、传统色彩；而 “Connie” 在20世纪中期后广泛流行，更具现代感和流行文化辨识度，如电影、音乐中的角色命名。"
    }
  ]
}