{
  "word": "jeez",
  "pronunciation": "jeez",
  "concise_definition": "interj. 天哪, 哎呀, 哇 (表达惊讶、烦躁或不满)",
  "forms": {
    "variants": [
      "geez",
      "jeezus",
      "jesus"
    ]
  },
  "definitions": [
    {
      "pos": "interjection",
      "explanation_en": "An informal exclamation used to express surprise, frustration, annoyance, or disbelief, often as a milder substitute for stronger swear words like 'Jesus' or 'damn'.",
      "explanation_cn": "一种非正式的感叹词，用于表达惊讶、沮丧、恼怒或难以置信，常作为对 'Jesus' 或 'damn' 等更强脏话的委婉替代。",
      "example_en": "Jeez, I can't believe you forgot my birthday again!",
      "example_cn": "天哪，你居然又忘了我的生日！"
    },
    {
      "pos": "interjection",
      "explanation_en": "Used to emphasize the intensity or absurdity of a situation, often with a tone of exasperation or sarcasm.",
      "explanation_cn": "用于强调某种情况的强烈程度或荒谬性，常带有不耐烦或讽刺的语气。",
      "example_en": "Jeez, it’s been raining for three days straight—when is this going to end?",
      "example_cn": "哎呀，都连着下了三天雨了——这什么时候才能停啊？"
    }
  ],
  "comparison": [
    {
      "word_to_compare": "wow",
      "analysis": "“Wow” (哇) 主要表达正面的惊叹或赞赏，语气较积极；而 “jeez” 多用于负面情绪，如恼火、无奈或失望，语气更消极或讽刺。"
    },
    {
      "word_to_compare": "oh my god",
      "analysis": "“Oh my god” (我的天啊) 情感强度更高，常用于震惊或极度惊讶，有时带有宗教色彩；“jeez” 更口语化、轻度，是避免直接使用神名的委婉说法，语气更随意、日常。"
    },
    {
      "word_to_compare": "heck",
      "analysis": "“Heck” (见鬼) 是对 'hell' 的委婉替代，语气较温和，多用于表达轻微的不满；“jeez” 则更侧重情绪的爆发，常用于表达更强烈的烦躁或难以置信，语义范围更广。"
    }
  ]
}