{
  "word": "nicaragua",
  "pronunciation": "nee·kə·rɑː·ɡwə",
  "concise_definition": "n. 尼加拉瓜（中美洲国家）",
  "forms": {
    "proper_noun": "Nicaragua"
  },
  "definitions": [
    {
      "pos": "noun",
      "explanation_en": "A country in Central America, bordered by Honduras to the north and Costa Rica to the south, with coastlines on both the Pacific Ocean and the Caribbean Sea. It is known for its lakes, volcanoes, and rich biodiversity.",
      "explanation_cn": "位于中美洲的一个国家，北邻洪都拉斯，南接哥斯达黎加，西临太平洋，东濒加勒比海。以湖泊、火山和丰富的生物多样性而闻名。",
      "example_en": "Nicaragua is home to Lake Nicaragua, the largest freshwater lake in Central America.",
      "example_cn": "尼加拉瓜拥有中美洲最大的淡水湖——尼加拉瓜湖。"
    },
    {
      "pos": "noun",
      "explanation_en": "The official name of the country is the Republic of Nicaragua; its people are called Nicaraguans, and its capital is Managua.",
      "explanation_cn": "该国的正式名称为尼加拉瓜共和国，其国民称为尼加拉瓜人，首都是马那瓜。",
      "example_en": "Many Nicaraguans have migrated to the United States seeking better economic opportunities.",
      "example_cn": "许多尼加拉瓜人移民到美国，以寻求更好的经济机会。"
    }
  ],
  "comparison": [
    {
      "word_to_compare": "honduras",
      "analysis": "“Honduras”（洪都拉斯）是尼加拉瓜北部的邻国，两者同属中美洲，语言和文化相似，但洪都拉斯的经济更依赖农业出口，而尼加拉瓜拥有更多火山地貌和湖泊资源。"
    },
    {
      "word_to_compare": "costa rica",
      "analysis": "“Costa Rica”（哥斯达黎加）位于尼加拉瓜南部，以政治稳定、高教育水平和生态保护著称，是中美洲最富裕的国家之一；相比之下，尼加拉瓜经济较落后，但自然景观更具原始野性。"
    },
    {
      "word_to_compare": "panama",
      "analysis": "“Panama”（巴拿马）虽同为中美洲国家，但地理位置更靠南，以巴拿马运河闻名，经济高度依赖航运和金融；而尼加拉瓜没有类似的战略性水道，其发展更依赖农业和旅游业。"
    }
  ]
}